autoclustal/README.md
autoclustal/version.txt
autoclustal/bin/__init__.py
autoclustal/bin/autoclustal.py
autoclustal/bin/create_demo_data.py
autoclustal/bin/grapher.py
autoclustal/bin/visualize.py
autoclustal/conf/base.config
autoclustal/conf/igenomes.config
autoclustal/conf/modules.config
autoclustal/conf/test.config
autoclustal/conf/test_full.config
autoclustal/modules/__init__.py
autoclustal/modules/alignment.py
autoclustal/modules/analysis.py
autoclustal/modules/blast_search.py
autoclustal/modules/clustering.py
autoclustal/modules/phylogeny.py
autoclustal/modules/sequence_handler.py
autoclustal/modules/simple_analysis.py
autoclustal-1.0.5.dist-info/licenses/LICENSE
autoclustal-1.0.5.dist-info/METADATA
autoclustal-1.0.5.dist-info/WHEEL
autoclustal-1.0.5.dist-info/entry_points.txt
autoclustal-1.0.5.dist-info/top_level.txt
autoclustal-1.0.5.dist-info/RECORD
