Metadata-Version: 2.4
Name: autoclustal
Version: 1.0.5
Summary: Comprehensive bioinformatics pipeline for sequence analysis, clustering, phylogeny, and BLAST annotation
Author-email: Stella Hartono <srhartono@ucdavis.edu>
License-Expression: MIT
Project-URL: Homepage, https://github.com/srhartono/autoclustal
Project-URL: Bug Tracker, https://github.com/srhartono/autoclustal/issues
Project-URL: Documentation, https://github.com/srhartono/autoclustal#readme
Project-URL: Source Code, https://github.com/srhartono/autoclustal
Keywords: bioinformatics,phylogeny,clustering,blast,sequence-analysis,alignment
Classifier: Development Status :: 4 - Beta
Classifier: Intended Audience :: Science/Research
Classifier: Topic :: Scientific/Engineering :: Bio-Informatics
Classifier: Programming Language :: Python :: 3
Classifier: Programming Language :: Python :: 3.8
Classifier: Programming Language :: Python :: 3.9
Classifier: Programming Language :: Python :: 3.10
Classifier: Programming Language :: Python :: 3.11
Classifier: Programming Language :: Python :: 3.12
Classifier: Operating System :: OS Independent
Requires-Python: >=3.8
License-File: LICENSE
Requires-Dist: biopython>=1.81
Requires-Dist: pandas>=1.3.0
Requires-Dist: numpy>=1.21.0
Requires-Dist: matplotlib>=3.5.0
Requires-Dist: seaborn>=0.11.0
Requires-Dist: scikit-learn>=1.0.0
Requires-Dist: requests>=2.25.0
Requires-Dist: plotly>=5.0.0
Dynamic: license-file
